.gitignore
CHANGELOG.md
LICENSE
README.md
setup.py
docs/Makefile
docs/make.bat
docs/source/API.rst
docs/source/conf.py
docs/source/index.rst
examples/before_after.png
examples/examples.ipynb
examples/simple_example.png
plotannot/__init__.py
plotannot/code.py
plotannot/functions.py
plotannot.egg-info/PKG-INFO
plotannot.egg-info/SOURCES.txt
plotannot.egg-info/dependency_links.txt
plotannot.egg-info/requires.txt
plotannot.egg-info/top_level.txt