Metadata-Version: 2.1
Name: plotannot
Version: 0.1.0
Summary: UNKNOWN
Home-page: https://github.com/msbentsen/plotannot
Author: Mette Bentsen
Author-email: mette.bentsen@mpi-bn.mpg.de
License: MIT
Platform: UNKNOWN
Classifier: License :: OSI Approved :: MIT License
Classifier: Intended Audience :: Science/Research
Classifier: Topic :: Scientific/Engineering :: Visualization
Classifier: Programming Language :: Python :: 3
License-File: LICENSE
